langlens/__init__.py
langlens/__main__.py
langlens/callbacks.py
langlens/cli.py
langlens/viewer/server.py
langlens/viewer/static/200.html
langlens/viewer/static/favicon.svg
langlens/viewer/static/icon.png
langlens/viewer/static/index.html
langlens/viewer/static/logo.svg
langlens/viewer/static/workflow_log.json
langlens/viewer/static/_app/env.js
langlens/viewer/static/_app/version.json
langlens/viewer/static/_app/immutable/assets/0.Ct7mucqJ.css
langlens/viewer/static/_app/immutable/assets/2.GdBltS-k.css
langlens/viewer/static/_app/immutable/chunks/BHpEsMCF.js
langlens/viewer/static/_app/immutable/chunks/BnUNjuXp.js
langlens/viewer/static/_app/immutable/chunks/Ci0TUjzZ.js
langlens/viewer/static/_app/immutable/chunks/Ct9u_a3k.js
langlens/viewer/static/_app/immutable/chunks/DJXACzzb.js
langlens/viewer/static/_app/immutable/chunks/DZUMnSdD.js
langlens/viewer/static/_app/immutable/chunks/DiRAknyg.js
langlens/viewer/static/_app/immutable/chunks/DuTZDju-.js
langlens/viewer/static/_app/immutable/chunks/YqVQlPzs.js
langlens/viewer/static/_app/immutable/entry/app.BEJOBrR8.js
langlens/viewer/static/_app/immutable/entry/start.CMh9Aybp.js
langlens/viewer/static/_app/immutable/nodes/0.n02Ieo9O.js
langlens/viewer/static/_app/immutable/nodes/1.B1X8Zs9y.js
langlens/viewer/static/_app/immutable/nodes/2.CTC1kP6l.js
langlens/viewer/static/fonts/JetBrainsMono-Bold.ttf
langlens/viewer/static/fonts/PlusJakartaSans-Bold.ttf
langlens/viewer/static/fonts/PlusJakartaSans-ExtraBold.ttf
langlens-0.1.2.dist-info/licenses/LICENSE
langlens-0.1.2.dist-info/METADATA
langlens-0.1.2.dist-info/WHEEL
langlens-0.1.2.dist-info/entry_points.txt
langlens-0.1.2.dist-info/top_level.txt
langlens-0.1.2.dist-info/RECORD
