Metadata-Version: 2.4
Name: langlens
Version: 0.1.2
Summary: A visual tracer and debugger for LangChain and LangGraph
Project-URL: Homepage, https://github.com/LETHEVIET/langlens
Project-URL: Repository, https://github.com/LETHEVIET/langlens
Project-URL: Issues, https://github.com/LETHEVIET/langlens/issues
Requires-Python: >=3.10
License-File: LICENSE
Requires-Dist: langchain-core
Provides-Extra: demo
Requires-Dist: langchain[google-genai]>=1.2.2; extra == "demo"
Requires-Dist: langchain-ollama>=1.0.1; extra == "demo"
Requires-Dist: langgraph-cli[inmem]>=0.4.11; extra == "demo"
Requires-Dist: langchain-groq>=1.1.1; extra == "demo"
Requires-Dist: python-dotenv; extra == "demo"
Dynamic: license-file
